guardcoreapi/__init__.py
guardcoreapi/manager.py
guardcoreapi/core/__init__.py
guardcoreapi/core/exceptions.py
guardcoreapi/core/request.py
guardcoreapi/types/__init__.py
guardcoreapi/types/admins.py
guardcoreapi/types/nodes.py
guardcoreapi/types/services.py
guardcoreapi/types/stats.py
guardcoreapi/types/subscriptions.py
guardcoreapi-0.4.0.dist-info/licenses/LICENSE
guardcoreapi-0.4.0.dist-info/METADATA
guardcoreapi-0.4.0.dist-info/WHEEL
guardcoreapi-0.4.0.dist-info/top_level.txt
guardcoreapi-0.4.0.dist-info/RECORD
