Metadata-Version: 2.4
Name: guardcoreapi
Version: 0.4.0
Summary: Guard Management Core Api Python lib
Requires-Python: >=3.11
License-File: LICENSE
Requires-Dist: aiohttp>=3.13.1
Requires-Dist: pydantic>=2.12.3
Dynamic: license-file
